gdot/__init__.py
gdot/__main__.py
gdot/commands.py
gdot/neofetch.py
gdot-0.0.2.dist-info/LICENSE
gdot-0.0.2.dist-info/METADATA
gdot-0.0.2.dist-info/WHEEL
gdot-0.0.2.dist-info/entry_points.txt
gdot-0.0.2.dist-info/top_level.txt
gdot-0.0.2.dist-info/RECORD
